[
  {
    "id": "mt7b4-s3-01",
    "q": "Garis yang selalu sama jarak disebut …",
    "options": [
      "Berpotongan",
      "Transversal",
      "Sejajar",
      "Berimpit"
    ],
    "answer": 2,
    "explain": "Sejajar jarak konstan."
  },
  {
    "id": "mt7b4-s3-02",
    "q": "Sudut 30 derajat termasuk …",
    "options": [
      "Refleks",
      "Tumpul",
      "Siku-siku",
      "Lancip"
    ],
    "answer": 3,
    "explain": "Kurang dari 90."
  },
  {
    "id": "mt7b4-s3-03",
    "q": "Sudut 270 derajat termasuk …",
    "options": [
      "Lancip",
      "Siku-siku",
      "Refleks",
      "Tumpul"
    ],
    "answer": 2,
    "explain": "Antara 180-360."
  },
  {
    "id": "mt7b4-s3-04",
    "q": "Sudut bertolak belakang terbentuk oleh …",
    "options": [
      "Dua garis berimpit",
      "Dua garis tak berhingga",
      "Dua garis sejajar",
      "Dua garis berpotongan"
    ],
    "answer": 3,
    "explain": "Perpotongan garis."
  },
  {
    "id": "mt7b4-s3-05",
    "q": "Pada garis sejajar, sudut sehadap 85 berarti sudut sehadap lain …",
    "options": [
      "95",
      "45",
      "180",
      "85"
    ],
    "answer": 3,
    "explain": "Sehadap kongruen."
  },
  {
    "id": "mt7b4-s3-06",
    "q": "Sudut sepihak dalam jika satu 120, lainnya …",
    "options": [
      "120",
      "60",
      "30",
      "90"
    ],
    "answer": 1,
    "explain": "Jumlah 180."
  },
  {
    "id": "mt7b4-s3-07",
    "q": "Sudut bersebrangan luar jika satu 70, lainnya …",
    "options": [
      "90",
      "110",
      "70",
      "50"
    ],
    "answer": 2,
    "explain": "Alternate exterior kongruen."
  },
  {
    "id": "mt7b4-s3-08",
    "q": "Sudut berpelurus 150, pasangan …",
    "options": [
      "90",
      "150",
      "60",
      "30"
    ],
    "answer": 3,
    "explain": "180−150=30."
  },
  {
    "id": "mt7b4-s3-09",
    "q": "Busur derajat skala luar dibaca dari …",
    "options": [
      "0 di kiri",
      "0 di kanan",
      "180 di tengah",
      "90 di atas"
    ],
    "answer": 0,
    "explain": "Skala luar mulai kiri."
  },
  {
    "id": "mt7b4-s3-10",
    "q": "Busur derajat skala dalam dibaca dari …",
    "options": [
      "180 di tengah",
      "90 di bawah",
      "0 di kiri",
      "0 di kanan"
    ],
    "answer": 3,
    "explain": "Skala dalam mulai kanan."
  },
  {
    "id": "mt7b4-s3-11",
    "q": "Jika dua garis sejajar, sudut bersebrangan dalam kongruen karena …",
    "options": [
      "Berpelurus",
      "Refleks",
      "Sudut sejenis",
      "Random"
    ],
    "answer": 2,
    "explain": "Transversal pada garis sejajar."
  },
  {
    "id": "mt7b4-s3-12",
    "q": "Menambah peredam suara di studio menggunakan konsep …",
    "options": [
      "Sudut tumpul",
      "Garis sejajar",
      "Sudut pantul",
      "Garis transversal"
    ],
    "answer": 2,
    "explain": "Pantulan sudut dikurangi bahan."
  },
  {
    "id": "mt7b4-s3-13",
    "q": "Sudut 0 derajat disebut …",
    "options": [
      "Lancip",
      "Siku-siku",
      "Sudut nol",
      "Refleks"
    ],
    "answer": 2,
    "explain": "Tidak ada pembukaan."
  },
  {
    "id": "mt7b4-s3-14",
    "q": "Sudut 180 derajat disebut …",
    "options": [
      "Siku-siku",
      "Tumpul",
      "Sudut lurus",
      "Refleks"
    ],
    "answer": 2,
    "explain": "Garis lurus 180."
  },
  {
    "id": "mt7b4-s3-15",
    "q": "Jika garis a sejajar b, transversal c, sudut sepihak luar 1 dan …",
    "options": [
      "3",
      "6",
      "7",
      "2"
    ],
    "answer": 2,
    "explain": "Sepihak luar sisi sama."
  },
  {
    "id": "mt7b4-s3-16",
    "q": "Menghitung sudut hilang: sudut lurus 180, diketahui 120. Hilang …",
    "options": [
      "30",
      "120",
      "90",
      "60"
    ],
    "answer": 3,
    "explain": "180−120=60."
  },
  {
    "id": "mt7b4-s3-17",
    "q": "Menghitung sudut di segitiga, dua sudut 50 dan 60. Sudut ketiga …",
    "options": [
      "60",
      "70",
      "80",
      "90"
    ],
    "answer": 1,
    "explain": "180−110=70."
  },
  {
    "id": "mt7b4-s3-18",
    "q": "Garis tegak lurus membentuk sudut …",
    "options": [
      "180 derajat",
      "60 derajat",
      "120 derajat",
      "90 derajat"
    ],
    "answer": 3,
    "explain": "Tegak lurus = siku-siku."
  },
  {
    "id": "mt7b4-s3-19",
    "q": "Sudut refleks 200 pasangan berpelurus …",
    "options": [
      "200",
      "Tidak mungkin",
      "20",
      "160"
    ],
    "answer": 1,
    "explain": "Refleks >180 tidak punya pasangan lurus di garis sama."
  },
  {
    "id": "mt7b4-s3-20",
    "q": "Sudut 135 derajat tergolong …",
    "options": [
      "Refleks",
      "Lancip",
      "Siku",
      "Tumpul"
    ],
    "answer": 3,
    "explain": "Di antara 90-180."
  }
]